wpclient/__init__.py
wpclient/cli.py
wpclient/client.py
wpclient/wpclient.py
wpclient/api/__init__.py
wpclient/api/exceptions.py
wpclient/api/functions.py
wpclient/api/singleton.py
wpclient/api/endpoints/__init__.py
wpclient/api/endpoints/categories.py
wpclient/api/endpoints/crud.py
wpclient/api/endpoints/manager.py
wpclient/api/endpoints/media.py
wpclient/api/endpoints/pages.py
wpclient/api/endpoints/posts.py
wpclient/api/endpoints/tags.py
wpclient/api/sync/__init__.py
wpclient/api/sync/categories.py
wpclient/api/sync/client.py
wpclient/api/sync/crud.py
wpclient/api/sync/media.py
wpclient/api/sync/posts.py
wpclient/api/sync/tags.py
wpclient/authentication/__init__.py
wpclient/authentication/jwt.py
wpclient/models/__init__.py
wpclient/models/category.py
wpclient/models/media.py
wpclient/models/page.py
wpclient/models/post.py
wpclient/models/tag.py
wpclient-0.3.0.dist-info/AUTHORS.rst
wpclient-0.3.0.dist-info/LICENSE
wpclient-0.3.0.dist-info/METADATA
wpclient-0.3.0.dist-info/WHEEL
wpclient-0.3.0.dist-info/top_level.txt
wpclient-0.3.0.dist-info/RECORD
