Metadata-Version: 2.1
Name: wpclient
Version: 0.3.0
Summary: WordPress REST API client with async support
Home-page: https://github.com/rguillermo/wpclient
Author: Guillermo Reyes
Author-email: jguillermo.dev@gmail.com
License: MIT license
Keywords: wpclient,async,aiohttp,requests,wordpress,api
Platform: UNKNOWN
Classifier: Development Status :: 2 - Pre-Alpha
Classifier: Intended Audience :: Developers
Classifier: License :: OSI Approved :: MIT License
Classifier: Natural Language :: English
Classifier: Programming Language :: Python :: 3
Classifier: Programming Language :: Python :: 3.9
Requires-Python: >=3.9
License-File: LICENSE
License-File: AUTHORS.rst
Requires-Dist: requests (>=2.26.0)
Requires-Dist: pydantic (>=1.8.2)
Requires-Dist: aiohttp (>=3.8.1)
Requires-Dist: cchardet (>=2.1.7)
